<?xml version="1.0" encoding="UTF-8"?>
<!DOCTYPE urlrewrite PUBLIC "-//tuckey.org//DTD UrlRewrite 3.0//EN" "http://tuckey.org/res/dtds/urlrewrite3.0.dtd">
<!--
    Document   : urlrewrite.xml
    Created on : 19 March 2007, 14:43
    Author     : mick
    Version    : $Id$
    Description:
        Purpose of the document follows.
-->
<urlrewrite>
    <!-- Global rewrites applicable to every skin (sitesearch and country!) -->

    <!-- tomcat puts in the name of the welcome page -->
    <rule><from>^/index.jsp$</from><to>/</to></rule> 

    <!-- Everything non-specified falls back to the default search (unspecified c parameter) -->
    <!-- TODO more work is needed to exclude 
      - /robots.txt
      - /favicon.ico
      - /search/(.*)
      - /map/(.*)
      - /servlet/(.*)
      - /dtds/(.*)
      - /export/(.*)
      - /static/(.*)
      - /tradedoubler/(.*)
      - before enabling the following very generic rewrite.
      -->
    <!--rule><from>^/(.+)$</from><to>/search/?q=$1</to></rule-->
</urlrewrite>
